arithmetic_esben_andersen/__init__.py
arithmetic_esben_andersen/arithmetic_esben_andersen.py
arithmetic_esben_andersen-0.1.45.dist-info/METADATA
arithmetic_esben_andersen-0.1.45.dist-info/WHEEL
arithmetic_esben_andersen-0.1.45.dist-info/entry_points.txt
arithmetic_esben_andersen-0.1.45.dist-info/RECORD
