Metadata-Version: 2.4
Name: arithmetic-esben-andersen
Version: 0.1.45
Summary: test package
Author-email: Esben Scriver <esbenscriver@gmail.com>
Requires-Python: >=3.11
Requires-Dist: mypy>=1.17.1
Requires-Dist: ty>=0.0.1a19
